thoth/storages/__init__.py
thoth/storages/advisers.py
thoth/storages/advisers_cache.py
thoth/storages/analyses.py
thoth/storages/analyses_by_digest.py
thoth/storages/analyses_cache.py
thoth/storages/base.py
thoth/storages/buildlogs.py
thoth/storages/buildlogs_analyses.py
thoth/storages/buildlogs_analyses_cache.py
thoth/storages/ceph.py
thoth/storages/ceph_cache.py
thoth/storages/cli.py
thoth/storages/dependency_monkey_reports.py
thoth/storages/exceptions.py
thoth/storages/inspection_schema.py
thoth/storages/inspections.py
thoth/storages/observations.py
thoth/storages/package_analyses.py
thoth/storages/provenance.py
thoth/storages/provenance_cache.py
thoth/storages/py.typed
thoth/storages/result_base.py
thoth/storages/result_schema.py
thoth/storages/solvers.py
thoth/storages/sync.py
thoth/storages/data/alembic.ini
thoth/storages/data/alembic/env.py
thoth/storages/data/alembic/script.py.mako
thoth/storages/data/alembic/versions/079e1d92f9d4_add_is_external_to_packageextractrun.py
thoth/storages/data/alembic/versions/184e698fe2c2_artifact_should_link_just_to_entity.py
thoth/storages/data/alembic/versions/1ee67d9a7861_enable_nullable_limit_latest_versions.py
thoth/storages/data/alembic/versions/295358ee27b1_add_description_content_type_column_to_.py
thoth/storages/data/alembic/versions/331cbc965699_relax_constraints_for_.py
thoth/storages/data/alembic/versions/54d50b0eeb33_allow_nullable_references_for_software_.py
thoth/storages/data/alembic/versions/650a13fd0a08_robust_syncs.py
thoth/storages/data/alembic/versions/74f68dabbb46_sync_python_interpreters.py
thoth/storages/data/alembic/versions/7866a83369ff_created_tables_for_metadata_multi_part_.py
thoth/storages/data/alembic/versions/9168881dd125_initial_schema.py
thoth/storages/data/alembic/versions/9a8ce1e52efb_added_externalsoftwareenvironment_.py
thoth/storages/data/alembic/versions/a05ad6e1d0ca_drop_unique_constraint_in_depends_on_.py
thoth_storage-0.19.17.dist-info/METADATA
thoth_storage-0.19.17.dist-info/RECORD
thoth_storage-0.19.17.dist-info/WHEEL
thoth_storage-0.19.17.dist-info/entry_points.txt
thoth_storage-0.19.17.dist-info/top_level.txt
