Metadata-Version: 2.1
Name: thoth-storage
Version: 0.19.17
Summary: Storage and database adapters available in project Thoth
Home-page: https://github.com/thoth-station/storages
Author: Fridolin Pokorny
Author-email: fridolin@redhat.com
Maintainer: Francesco Murdaca
Maintainer-email: fmurdaca@redhat.com
License: GPLv3+
Platform: UNKNOWN
Requires-Dist: click
Requires-Dist: voluptuous
Requires-Dist: boto3
Requires-Dist: thoth-common
Requires-Dist: amun
Requires-Dist: python-dateutil
Requires-Dist: thoth-python
Requires-Dist: pyyaml
Requires-Dist: methodtools
Requires-Dist: sqlalchemy
Requires-Dist: psycopg2-binary
Requires-Dist: sqlalchemy-utils
Requires-Dist: alembic
